timeplus_connect/__init__.py
timeplus_connect/__version__.py
timeplus_connect/common.py
timeplus_connect/entry_points.py
timeplus_connect/json_impl.py
timeplus_connect/py.typed
timeplus_connect/cc_sqlalchemy/__init__.py
timeplus_connect/cc_sqlalchemy/dialect.py
timeplus_connect/cc_sqlalchemy/inspector.py
timeplus_connect/cc_sqlalchemy/datatypes/__init__.py
timeplus_connect/cc_sqlalchemy/datatypes/base.py
timeplus_connect/cc_sqlalchemy/datatypes/sqltypes.py
timeplus_connect/cc_sqlalchemy/ddl/__init__.py
timeplus_connect/cc_sqlalchemy/ddl/custom.py
timeplus_connect/cc_sqlalchemy/ddl/tableengine.py
timeplus_connect/cc_sqlalchemy/sql/__init__.py
timeplus_connect/cc_sqlalchemy/sql/ddlcompiler.py
timeplus_connect/cc_sqlalchemy/sql/preparer.py
timeplus_connect/datatypes/__init__.py
timeplus_connect/datatypes/base.py
timeplus_connect/datatypes/container.py
timeplus_connect/datatypes/dynamic.py
timeplus_connect/datatypes/format.py
timeplus_connect/datatypes/geometric.py
timeplus_connect/datatypes/network.py
timeplus_connect/datatypes/numeric.py
timeplus_connect/datatypes/postinit.py
timeplus_connect/datatypes/registry.py
timeplus_connect/datatypes/special.py
timeplus_connect/datatypes/string.py
timeplus_connect/datatypes/temporal.py
timeplus_connect/dbapi/__init__.py
timeplus_connect/dbapi/connection.py
timeplus_connect/dbapi/cursor.py
timeplus_connect/driver/__init__.py
timeplus_connect/driver/asyncclient.py
timeplus_connect/driver/binding.py
timeplus_connect/driver/buffer.py
timeplus_connect/driver/client.py
timeplus_connect/driver/common.py
timeplus_connect/driver/compression.py
timeplus_connect/driver/constants.py
timeplus_connect/driver/context.py
timeplus_connect/driver/ctypes.py
timeplus_connect/driver/dataconv.py
timeplus_connect/driver/ddl.py
timeplus_connect/driver/errors.py
timeplus_connect/driver/exceptions.py
timeplus_connect/driver/external.py
timeplus_connect/driver/httpclient.py
timeplus_connect/driver/httputil.py
timeplus_connect/driver/insert.py
timeplus_connect-0.8.17.dist-info/licenses/LICENSE
timeplus_connect-0.8.17.dist-info/METADATA
timeplus_connect-0.8.17.dist-info/WHEEL
timeplus_connect-0.8.17.dist-info/entry_points.txt
timeplus_connect-0.8.17.dist-info/top_level.txt
timeplus_connect-0.8.17.dist-info/RECORD
