Metadata-Version: 2.4
Name: timeplus-connect
Version: 0.8.17
Summary: Timeplus Database Driver for Python, Pandas, and Superset
Home-page: https://github.com/timeplus-io/timeplus-connect
Author: Timeplus Inc.
Author-email: eng@timeplus.com
License: Apache License 2.0
Keywords: timeplus,superset,sqlalchemy,http,driver
Classifier: Development Status :: 4 - Beta
Classifier: Intended Audience :: Developers
Classifier: License :: OSI Approved :: Apache Software License
Classifier: Programming Language :: Python :: 3.8
Classifier: Programming Language :: Python :: 3.9
Classifier: Programming Language :: Python :: 3.10
Classifier: Programming Language :: Python :: 3.11
Classifier: Programming Language :: Python :: 3.12
Classifier: Programming Language :: Python :: 3.13
Requires-Python: ~=3.8
License-File: LICENSE
Requires-Dist: certifi
Requires-Dist: urllib3>=1.26
Requires-Dist: pytz
Requires-Dist: zstandard
Requires-Dist: lz4
Provides-Extra: sqlalchemy
Requires-Dist: sqlalchemy<2.0,>1.3.21; extra == "sqlalchemy"
Provides-Extra: numpy
Requires-Dist: numpy; extra == "numpy"
Provides-Extra: pandas
Requires-Dist: pandas; extra == "pandas"
Provides-Extra: arrow
Requires-Dist: pyarrow; extra == "arrow"
Provides-Extra: orjson
Requires-Dist: orjson; extra == "orjson"
Provides-Extra: tzlocal
Requires-Dist: tzlocal>=4.0; extra == "tzlocal"
Dynamic: author
Dynamic: author-email
Dynamic: classifier
Dynamic: description
Dynamic: description-content-type
Dynamic: home-page
Dynamic: keywords
Dynamic: license
Dynamic: license-file
Dynamic: provides-extra
Dynamic: requires-dist
Dynamic: requires-python
Dynamic: summary
